fast_colorthief.py
fast_colorthief_backend.cpython-312-darwin.so
version.py
fast_colorthief-0.0.5.dist-info/METADATA
fast_colorthief-0.0.5.dist-info/WHEEL
fast_colorthief-0.0.5.dist-info/top_level.txt
fast_colorthief-0.0.5.dist-info/RECORD
