Metadata-Version: 2.1
Name: fast-colorthief
Version: 0.0.5
Summary: Dominant colors in image
Home-page: https://github.com/bedapisl/fast-colorthief
Author: Bedrich Pisl
Author-email: bedapisl@gmail.com
License: MIT
Platform: UNKNOWN
Requires-Dist: Pillow
Requires-Dist: numpy
